{
    "service_info":{
          "service_name":"vrqo",
          "service_type":"vrqo",
          "service_exe_path":"QueryOptimizer",
          "startup_time": 420
      },
    "deploy_info":
    {
        "deploy_step":{},
        "deploy_local_path":"/search/odin/tester/vrqo/"
    },
    "svn_info":{
        "username":"",
        "password":"",
        "svn_link": ""
    },
    "online_info":{
        "module_machine":"rsync.vrqo01.web.djt.ted",
        "module_path":"odin/search/odin/daemon/vrqo/",
        "module_conf":"odin/search/odin/daemon/vrqo/conf/vrqo_1djt.cfg"
    },
    "offline_server_info":[
            {
                "addr":"rsync.offvrqo01.in.sjs.ted",
                "username":"root",
                "password":"noSafeNoWork@2014",
                "deploy_path":"/search/odin/test/"
            },
            {
                "addr":"rsync.offvrqo02.in.sjs.ted",
                "username":"root",
                "password":"noSafeNoWork@2014",
                "deploy_path":"/search/odin/test/"
            },
            {
                "addr":"rsync.offvrqo03.in.sjs.ted",
                "username":"root",
                "password":"noSafeNoWork@2014",
                "deploy_path":"/search/odin/test/"
            },
            {
                "addr":"rsync.offvrqo04.in.sjs.ted",
                "username":"root",
                "password":"noSafeNoWork@2014",
                "deploy_path":"/search/odin/test/"
            }
    ],
    "offline_data_info":{
        "data_base_path":"/search/data/vrqo_data/",
        "data_modify_path":"",
        "data_script":"./proc/vrqo_data_deploy.py",
        "data_conf":"./conf/data_modify_template.json"
    },
    "config_modify_file":"./conf/config_modify_template.json"
}